{
  "info": {
    "_postman_id": "a3a6f0a8-2b26-4a63-9c31-7739a7b36933",
    "name": "idurar-erp-crm API",
    "schema": "https://schema.getpostman.com/json/collection/v2.1.0/collection.json"
  },
  "item": [
    {
      "name": "Taxes",
      "item": [
        {
          "name": "Create",
          "request": {
            "method": "POST",
            "header": [],
            "url": {
              "raw": "http://localhost:8888/api/taxes/create",
              "protocol": "http",
              "host": [
                "localhost"
              ],
              "port": "8888",
              "path": [
                "api",
                "taxes",
                "create"
              ]
            }
          },
          "response": []
        },
        {
          "name": "Read",
          "request": {
            "method": "GET",
            "header": [],
            "url": {
              "raw": "http://localhost:8888/api/taxes/read/:id",
              "protocol": "http",
              "host": [
                "localhost"
              ],
              "port": "8888",
              "path": [
                "api",
                "taxes",
                "read",
                ":id"
              ]
            }
          },
          "response": []
        },
        {
          "name": "Update",
          "request": {
            "method": "PATCH",
            "header": [],
            "url": {
              "raw": "http://localhost:8888/api/taxes/update/:id",
              "protocol": "http",
              "host": [
                "localhost"
              ],
              "port": "8888",
              "path": [
                "api",
                "taxes",
                "update",
                ":id"
              ]
            }
          },
          "response": []
        },
        {
          "name": "Delete",
          "request": {
            "method": "DELETE",
            "header": [],
            "url": {
              "raw": "http://localhost:8888/api/taxes/delete/:id",
              "protocol": "http",
              "host": [
                "localhost"
              ],
              "port": "8888",
              "path": [
                "api",
                "taxes",
                "delete",
                ":id"
              ]
            }
          },
          "response": []
        },
        {
          "name": "Search",
          "request": {
            "method": "GET",
            "header": [],
            "url": {
              "raw": "http://localhost:8888/api/taxes/search",
              "protocol": "http",
              "host": [
                "localhost"
              ],
              "port": "8888",
              "path": [
                "api",
                "taxes",
                "search"
              ]
            }
          },
          "response": []
        },
        {
          "name": "List",
          "request": {
            "method": "GET",
            "header": [],
            "url": {
              "raw": "http://localhost:8888/api/taxes/list",
              "protocol": "http",
              "host": [
                "localhost"
              ],
              "port": "8888",
              "path": [
                "api",
                "taxes",
                "list"
              ]
            }
          },
          "response": []
        },
        {
          "name": "List All",
          "request": {
            "method": "GET",
            "header": [],
            "url": {
              "raw": "http://localhost:8888/api/taxes/listAll",
              "protocol": "http",
              "host": [
                "localhost"
              ],
              "port": "8888",
              "path": [
                "api",
                "taxes",
                "listAll"
              ]
            }
          },
          "response": []
        },
        {
          "name": "Filter",
          "request": {
            "method": "GET",
            "header": [],
            "url": {
              "raw": "http://localhost:8888/api/taxes/filter",
              "protocol": "http",
              "host": [
                "localhost"
              ],
              "port": "8888",
              "path": [
                "api",
                "taxes",
                "filter"
              ]
            }
          },
          "response": []
        },
        {
          "name": "Summary",
          "request": {
            "method": "GET",
            "header": [],
            "url": {
              "raw": "http://localhost:8888/api/taxes/summary",
              "protocol": "http",
              "host": [
                "localhost"
              ],
              "port": "8888",
              "path": [
                "api",
                "taxes",
                "summary"
              ]
            }
          },
          "response": []
        }
      ]
    },
    {
      "name": "Quote",
      "item": [
        {
          "name": "Create",
          "request": {
            "method": "POST",
            "header": [],
            "url": {
              "raw": "http://localhost:8888/api/quote/create",
              "protocol": "http",
              "host": [
                "localhost"
              ],
              "port": "8888",
              "path": [
                "api",
                "quote",
                "create"
              ]
            }
          },
          "response": []
        },
        {
          "name": "Read",
          "request": {
            "method": "GET",
            "header": [],
            "url": {
              "raw": "http://localhost:8888/api/quote/read/:id",
              "protocol": "http",
              "host": [
                "localhost"
              ],
              "port": "8888",
              "path": [
                "api",
                "quote",
                "read",
                ":id"
              ]
            }
          },
          "response": []
        },
        {
          "name": "Update",
          "request": {
            "method": "PATCH",
            "header": [],
            "url": {
              "raw": "http://localhost:8888/api/quote/update/:id",
              "protocol": "http",
              "host": [
                "localhost"
              ],
              "port": "8888",
              "path": [
                "api",
                "quote",
                "update",
                ":id"
              ]
            }
          },
          "response": []
        },
        {
          "name": "Delete",
          "request": {
            "method": "DELETE",
            "header": [],
            "url": {
              "raw": "http://localhost:8888/api/quote/delete/:id",
              "protocol": "http",
              "host": [
                "localhost"
              ],
              "port": "8888",
              "path": [
                "api",
                "quote",
                "delete",
                ":id"
              ]
            }
          },
          "response": []
        },
        {
          "name": "Search",
          "request": {
            "method": "GET",
            "header": [],
            "url": {
              "raw": "http://localhost:8888/api/quote/search",
              "protocol": "http",
              "host": [
                "localhost"
              ],
              "port": "8888",
              "path": [
                "api",
                "quote",
                "search"
              ]
            }
          },
          "response": []
        },
        {
          "name": "List",
          "request": {
            "method": "GET",
            "header": [],
            "url": {
              "raw": "http://localhost:8888/api/quote/list",
              "protocol": "http",
              "host": [
                "localhost"
              ],
              "port": "8888",
              "path": [
                "api",
                "quote",
                "list"
              ]
            }
          },
          "response": []
        },
        {
          "name": "List All",
          "request": {
            "method": "GET",
            "header": [],
            "url": {
              "raw": "http://localhost:8888/api/quote/listAll",
              "protocol": "http",
              "host": [
                "localhost"
              ],
              "port": "8888",
              "path": [
                "api",
                "quote",
                "listAll"
              ]
            }
          },
          "response": []
        },
        {
          "name": "Filter",
          "request": {
            "method": "GET",
            "header": [],
            "url": {
              "raw": "http://localhost:8888/api/quote/filter",
              "protocol": "http",
              "host": [
                "localhost"
              ],
              "port": "8888",
              "path": [
                "api",
                "quote",
                "filter"
              ]
            }
          },
          "response": []
        },
        {
          "name": "Summary",
          "request": {
            "method": "GET",
            "header": [],
            "url": {
              "raw": "http://localhost:8888/api/quote/summary",
              "protocol": "http",
              "host": [
                "localhost"
              ],
              "port": "8888",
              "path": [
                "api",
                "quote",
                "summary"
              ]
            }
          },
          "response": []
        },
        {
          "name": "Mail",
          "request": {
            "method": "POST",
            "header": [],
            "url": {
              "raw": "http://localhost:8888/api/quote/mail",
              "protocol": "http",
              "host": [
                "localhost"
              ],
              "port": "8888",
              "path": [
                "api",
                "quote",
                "mail"
              ]
            }
          },
          "response": []
        },
        {
          "name": "Convert",
          "request": {
            "method": "GET",
            "header": [],
            "url": {
              "raw": "http://localhost:8888/api/quote/convert/:id",
              "protocol": "http",
              "host": [
                "localhost"
              ],
              "port": "8888",
              "path": [
                "api",
                "quote",
                "convert",
                ":id"
              ]
            }
          },
          "response": []
        }
      ]
    },
    {
      "name": "Paymentmode",
      "item": [
        {
          "name": "Create",
          "request": {
            "method": "POST",
            "header": [],
            "url": {
              "raw": "http://localhost:8888/api/paymentmode/create",
              "protocol": "http",
              "host": [
                "localhost"
              ],
              "port": "8888",
              "path": [
                "api",
                "paymentmode",
                "create"
              ]
            }
          },
          "response": []
        },
        {
          "name": "Read",
          "request": {
            "method": "GET",
            "header": [],
            "url": {
              "raw": "http://localhost:8888/api/paymentmode/read/:id",
              "protocol": "http",
              "host": [
                "localhost"
              ],
              "port": "8888",
              "path": [
                "api",
                "paymentmode",
                "read",
                ":id"
              ]
            }
          },
          "response": []
        },
        {
          "name": "Update",
          "request": {
            "method": "PATCH",
            "header": [],
            "url": {
              "raw": "http://localhost:8888/api/paymentmode/update/:id",
              "protocol": "http",
              "host": [
                "localhost"
              ],
              "port": "8888",
              "path": [
                "api",
                "paymentmode",
                "update",
                ":id"
              ]
            }
          },
          "response": []
        },
        {
          "name": "Delete",
          "request": {
            "method": "DELETE",
            "header": [],
            "url": {
              "raw": "http://localhost:8888/api/paymentmode/delete/:id",
              "protocol": "http",
              "host": [
                "localhost"
              ],
              "port": "8888",
              "path": [
                "api",
                "paymentmode",
                "delete",
                ":id"
              ]
            }
          },
          "response": []
        },
        {
          "name": "Search",
          "request": {
            "method": "GET",
            "header": [],
            "url": {
              "raw": "http://localhost:8888/api/paymentmode/search",
              "protocol": "http",
              "host": [
                "localhost"
              ],
              "port": "8888",
              "path": [
                "api",
                "paymentmode",
                "search"
              ]
            }
          },
          "response": []
        },
        {
          "name": "List",
          "request": {
            "method": "GET",
            "header": [],
            "url": {
              "raw": "http://localhost:8888/api/paymentmode/list",
              "protocol": "http",
              "host": [
                "localhost"
              ],
              "port": "8888",
              "path": [
                "api",
                "paymentmode",
                "list"
              ]
            }
          },
          "response": []
        },
        {
          "name": "List All",
          "request": {
            "method": "GET",
            "header": [],
            "url": {
              "raw": "http://localhost:8888/api/paymentmode/listAll",
              "protocol": "http",
              "host": [
                "localhost"
              ],
              "port": "8888",
              "path": [
                "api",
                "paymentmode",
                "listAll"
              ]
            }
          },
          "response": []
        },
        {
          "name": "Filter",
          "request": {
            "method": "GET",
            "header": [],
            "url": {
              "raw": "http://localhost:8888/api/paymentmode/filter",
              "protocol": "http",
              "host": [
                "localhost"
              ],
              "port": "8888",
              "path": [
                "api",
                "paymentmode",
                "filter"
              ]
            }
          },
          "response": []
        },
        {
          "name": "Summary",
          "request": {
            "method": "GET",
            "header": [],
            "url": {
              "raw": "http://localhost:8888/api/paymentmode/summary",
              "protocol": "http",
              "host": [
                "localhost"
              ],
              "port": "8888",
              "path": [
                "api",
                "paymentmode",
                "summary"
              ]
            }
          },
          "response": []
        }
      ]
    },
    {
      "name": "Payment",
      "item": [
        {
          "name": "Create",
          "request": {
            "method": "POST",
            "header": [],
            "url": {
              "raw": "http://localhost:8888/api/payment/create",
              "protocol": "http",
              "host": [
                "localhost"
              ],
              "port": "8888",
              "path": [
                "api",
                "payment",
                "create"
              ]
            }
          },
          "response": []
        },
        {
          "name": "Read",
          "request": {
            "method": "GET",
            "header": [],
            "url": {
              "raw": "http://localhost:8888/api/payment/read/:id",
              "protocol": "http",
              "host": [
                "localhost"
              ],
              "port": "8888",
              "path": [
                "api",
                "payment",
                "read",
                ":id"
              ]
            }
          },
          "response": []
        },
        {
          "name": "Update",
          "request": {
            "method": "PATCH",
            "header": [],
            "url": {
              "raw": "http://localhost:8888/api/payment/update/:id",
              "protocol": "http",
              "host": [
                "localhost"
              ],
              "port": "8888",
              "path": [
                "api",
                "payment",
                "update",
                ":id"
              ]
            }
          },
          "response": []
        },
        {
          "name": "Delete",
          "request": {
            "method": "DELETE",
            "header": [],
            "url": {
              "raw": "http://localhost:8888/api/payment/delete/:id",
              "protocol": "http",
              "host": [
                "localhost"
              ],
              "port": "8888",
              "path": [
                "api",
                "payment",
                "delete",
                ":id"
              ]
            }
          },
          "response": []
        },
        {
          "name": "Search",
          "request": {
            "method": "GET",
            "header": [],
            "url": {
              "raw": "http://localhost:8888/api/payment/search",
              "protocol": "http",
              "host": [
                "localhost"
              ],
              "port": "8888",
              "path": [
                "api",
                "payment",
                "search"
              ]
            }
          },
          "response": []
        },
        {
          "name": "List",
          "request": {
            "method": "GET",
            "header": [],
            "url": {
              "raw": "http://localhost:8888/api/payment/list",
              "protocol": "http",
              "host": [
                "localhost"
              ],
              "port": "8888",
              "path": [
                "api",
                "payment",
                "list"
              ]
            }
          },
          "response": []
        },
        {
          "name": "List All",
          "request": {
            "method": "GET",
            "header": [],
            "url": {
              "raw": "http://localhost:8888/api/payment/listAll",
              "protocol": "http",
              "host": [
                "localhost"
              ],
              "port": "8888",
              "path": [
                "api",
                "payment",
                "listAll"
              ]
            }
          },
          "response": []
        },
        {
          "name": "Filter",
          "request": {
            "method": "GET",
            "header": [],
            "url": {
              "raw": "http://localhost:8888/api/payment/filter",
              "protocol": "http",
              "host": [
                "localhost"
              ],
              "port": "8888",
              "path": [
                "api",
                "payment",
                "filter"
              ]
            }
          },
          "response": []
        },
        {
          "name": "Summary",
          "request": {
            "method": "GET",
            "header": [],
            "url": {
              "raw": "http://localhost:8888/api/payment/summary",
              "protocol": "http",
              "host": [
                "localhost"
              ],
              "port": "8888",
              "path": [
                "api",
                "payment",
                "summary"
              ]
            }
          },
          "response": []
        },
        {
          "name": "Mail",
          "request": {
            "method": "POST",
            "header": [],
            "url": {
              "raw": "http://localhost:8888/api/payment/mail",
              "protocol": "http",
              "host": [
                "localhost"
              ],
              "port": "8888",
              "path": [
                "api",
                "payment",
                "mail"
              ]
            }
          },
          "response": []
        }
      ]
    },
    {
      "name": "Invoice",
      "item": [
        {
          "name": "Create",
          "request": {
            "method": "POST",
            "header": [],
            "url": {
              "raw": "http://localhost:8888/api/invoice/create",
              "protocol": "http",
              "host": [
                "localhost"
              ],
              "port": "8888",
              "path": [
                "api",
                "invoice",
                "create"
              ]
            }
          },
          "response": []
        },
        {
          "name": "Read",
          "request": {
            "method": "GET",
            "header": [],
            "url": {
              "raw": "http://localhost:8888/api/invoice/read/:id",
              "protocol": "http",
              "host": [
                "localhost"
              ],
              "port": "8888",
              "path": [
                "api",
                "invoice",
                "read",
                ":id"
              ]
            }
          },
          "response": []
        },
        {
          "name": "Update",
          "request": {
            "method": "PATCH",
            "header": [],
            "url": {
              "raw": "http://localhost:8888/api/invoice/update/:id",
              "protocol": "http",
              "host": [
                "localhost"
              ],
              "port": "8888",
              "path": [
                "api",
                "invoice",
                "update",
                ":id"
              ]
            }
          },
          "response": []
        },
        {
          "name": "Delete",
          "request": {
            "method": "DELETE",
            "header": [],
            "url": {
              "raw": "http://localhost:8888/api/invoice/delete/:id",
              "protocol": "http",
              "host": [
                "localhost"
              ],
              "port": "8888",
              "path": [
                "api",
                "invoice",
                "delete",
                ":id"
              ]
            }
          },
          "response": []
        },
        {
          "name": "Search",
          "request": {
            "method": "GET",
            "header": [],
            "url": {
              "raw": "http://localhost:8888/api/invoice/search",
              "protocol": "http",
              "host": [
                "localhost"
              ],
              "port": "8888",
              "path": [
                "api",
                "invoice",
                "search"
              ]
            }
          },
          "response": []
        },
        {
          "name": "List",
          "request": {
            "method": "GET",
            "header": [],
            "url": {
              "raw": "http://localhost:8888/api/invoice/list",
              "protocol": "http",
              "host": [
                "localhost"
              ],
              "port": "8888",
              "path": [
                "api",
                "invoice",
                "list"
              ]
            }
          },
          "response": []
        },
        {
          "name": "List All",
          "request": {
            "method": "GET",
            "header": [],
            "url": {
              "raw": "http://localhost:8888/api/invoice/listAll",
              "protocol": "http",
              "host": [
                "localhost"
              ],
              "port": "8888",
              "path": [
                "api",
                "invoice",
                "listAll"
              ]
            }
          },
          "response": []
        },
        {
          "name": "Filter",
          "request": {
            "method": "GET",
            "header": [],
            "url": {
              "raw": "http://localhost:8888/api/invoice/filter",
              "protocol": "http",
              "host": [
                "localhost"
              ],
              "port": "8888",
              "path": [
                "api",
                "invoice",
                "filter"
              ]
            }
          },
          "response": []
        },
        {
          "name": "Summary",
          "request": {
            "method": "GET",
            "header": [],
            "url": {
              "raw": "http://localhost:8888/api/invoice/summary",
              "protocol": "http",
              "host": [
                "localhost"
              ],
              "port": "8888",
              "path": [
                "api",
                "invoice",
                "summary"
              ]
            }
          },
          "response": []
        },
        {
          "name": "Mail",
          "request": {
            "method": "POST",
            "header": [],
            "url": {
              "raw": "http://localhost:8888/api/invoice/mail",
              "protocol": "http",
              "host": [
                "localhost"
              ],
              "port": "8888",
              "path": [
                "api",
                "invoice",
                "mail"
              ]
            }
          },
          "response": []
        }
      ]
    },
    {
      "name": "Client",
      "item": [
        {
          "name": "Create",
          "request": {
            "method": "POST",
            "header": [],
            "url": {
              "raw": "http://localhost:8888/api/client/create",
              "protocol": "http",
              "host": [
                "localhost"
              ],
              "port": "8888",
              "path": [
                "api",
                "client",
                "create"
              ]
            }
          },
          "response": []
        },
        {
          "name": "Read",
          "request": {
            "method": "GET",
            "header": [],
            "url": {
              "raw": "http://localhost:8888/api/client/read/:id",
              "protocol": "http",
              "host": [
                "localhost"
              ],
              "port": "8888",
              "path": [
                "api",
                "client",
                "read",
                ":id"
              ]
            }
          },
          "response": []
        },
        {
          "name": "Update",
          "request": {
            "method": "PATCH",
            "header": [],
            "url": {
              "raw": "http://localhost:8888/api/client/update/:id",
              "protocol": "http",
              "host": [
                "localhost"
              ],
              "port": "8888",
              "path": [
                "api",
                "client",
                "update",
                ":id"
              ]
            }
          },
          "response": []
        },
        {
          "name": "Delete",
          "request": {
            "method": "DELETE",
            "header": [],
            "url": {
              "raw": "http://localhost:8888/api/client/delete/:id",
              "protocol": "http",
              "host": [
                "localhost"
              ],
              "port": "8888",
              "path": [
                "api",
                "client",
                "delete",
                ":id"
              ]
            }
          },
          "response": []
        },
        {
          "name": "Search",
          "request": {
            "method": "GET",
            "header": [],
            "url": {
              "raw": "http://localhost:8888/api/client/search",
              "protocol": "http",
              "host": [
                "localhost"
              ],
              "port": "8888",
              "path": [
                "api",
                "client",
                "search"
              ]
            }
          },
          "response": []
        },
        {
          "name": "List",
          "request": {
            "method": "GET",
            "header": [],
            "url": {
              "raw": "http://localhost:8888/api/client/list",
              "protocol": "http",
              "host": [
                "localhost"
              ],
              "port": "8888",
              "path": [
                "api",
                "client",
                "list"
              ]
            }
          },
          "response": []
        },
        {
          "name": "List All",
          "request": {
            "method": "GET",
            "header": [],
            "url": {
              "raw": "http://localhost:8888/api/client/listAll",
              "protocol": "http",
              "host": [
                "localhost"
              ],
              "port": "8888",
              "path": [
                "api",
                "client",
                "listAll"
              ]
            }
          },
          "response": []
        },
        {
          "name": "Filter",
          "request": {
            "method": "GET",
            "header": [],
            "url": {
              "raw": "http://localhost:8888/api/client/filter",
              "protocol": "http",
              "host": [
                "localhost"
              ],
              "port": "8888",
              "path": [
                "api",
                "client",
                "filter"
              ]
            }
          },
          "response": []
        },
        {
          "name": "Summary",
          "request": {
            "method": "GET",
            "header": [],
            "url": {
              "raw": "http://localhost:8888/api/client/summary",
              "protocol": "http",
              "host": [
                "localhost"
              ],
              "port": "8888",
              "path": [
                "api",
                "client",
                "summary"
              ]
            }
          },
          "response": []
        }
      ]
    },
    {
      "name": "Auth",
      "item": [
        {
          "name": "Login",
          "request": {
            "method": "POST",
            "header": [],
            "url": {
              "raw": "http://localhost:8888/api/login",
              "protocol": "http",
              "host": [
                "localhost"
              ],
              "port": "8888",
              "path": [
                "api",
                "login"
              ]
            }
          },
          "response": []
        },
        {
          "name": "Forget Password",
          "request": {
            "method": "POST",
            "header": [],
            "url": {
              "raw": "http://localhost:8888/api/forgetpassword",
              "protocol": "http",
              "host": [
                "localhost"
              ],
              "port": "8888",
              "path": [
                "api",
                "forgetpassword"
              ]
            }
          },
          "response": []
        },
        {
          "name": "Reset Password",
          "request": {
            "method": "POST",
            "header": [],
            "url": {
              "raw": "http://localhost:8888/api/resetpassword",
              "protocol": "http",
              "host": [
                "localhost"
              ],
              "port": "8888",
              "path": [
                "api",
                "resetpassword"
              ]
            }
          },
          "response": []
        },
        {
          "name": "Logout",
          "request": {
            "method": "POST",
            "header": [],
            "url": {
              "raw": "http://localhost:8888/api/logout",
              "protocol": "http",
              "host": [
                "localhost"
              ],
              "port": "8888",
              "path": [
                "api",
                "logout"
              ]
            }
          },
          "response": []
        }
      ]
    },
    {
      "name": "Admin",
      "item": [
        {
          "name": "Read",
          "request": {
            "method": "GET",
            "header": [],
            "url": {
              "raw": "http://localhost:8888/api/admin/read/:id",
              "protocol": "http",
              "host": [
                "localhost"
              ],
              "port": "8888",
              "path": [
                "api",
                "admin",
                "read",
                ":id"
              ]
            }
          },
          "response": []
        },
        {
          "name": "Password Update",
          "request": {
            "method": "PATCH",
            "header": [],
            "url": {
              "raw": "http://localhost:8888/api/admin/password-update/:id",
              "protocol": "http",
              "host": [
                "localhost"
              ],
              "port": "8888",
              "path": [
                "api",
                "admin",
                "password-update",
                ":id"
              ]
            }
          },
          "response": []
        },
        {
          "name": "Profile Password",
          "request": {
            "method": "PATCH",
            "header": [],
            "url": {
              "raw": "http://localhost:8888/api/admin/profile/password",
              "protocol": "http",
              "host": [
                "localhost"
              ],
              "port": "8888",
              "path": [
                "api",
                "admin",
                "profile",
                "password"
              ]
            }
          },
          "response": []
        },
        {
          "name": "Profile Update",
          "request": {
            "method": "PATCH",
            "header": [],
            "url": {
              "raw": "http://localhost:8888/api/admin/profile/update",
              "protocol": "http",
              "host": [
                "localhost"
              ],
              "port": "8888",
              "path": [
                "api",
                "admin",
                "profile",
                "update"
              ]
            }
          },
          "response": []
        }
      ]
    },
    {
      "name": "Setting",
      "item": [
        {
          "name": "Create",
          "request": {
            "method": "POST",
            "header": [],
            "url": {
              "raw": "http://localhost:8888/api/setting/create",
              "protocol": "http",
              "host": [
                "localhost"
              ],
              "port": "8888",
              "path": [
                "api",
                "setting",
                "create"
              ]
            }
          },
          "response": []
        },
        {
          "name": "Read",
          "request": {
            "method": "GET",
            "header": [],
            "url": {
              "raw": "http://localhost:8888/api/setting/read/:id",
              "protocol": "http",
              "host": [
                "localhost"
              ],
              "port": "8888",
              "path": [
                "api",
                "setting",
                "read",
                ":id"
              ]
            }
          },
          "response": []
        },
        {
          "name": "Update",
          "request": {
            "method": "PATCH",
            "header": [],
            "url": {
              "raw": "http://localhost:8888/api/setting/update/:id",
              "protocol": "http",
              "host": [
                "localhost"
              ],
              "port": "8888",
              "path": [
                "api",
                "setting",
                "update",
                ":id"
              ]
            }
          },
          "response": []
        },
        {
          "name": "Search",
          "request": {
            "method": "GET",
            "header": [],
            "url": {
              "raw": "http://localhost:8888/api/setting/search",
              "protocol": "http",
              "host": [
                "localhost"
              ],
              "port": "8888",
              "path": [
                "api",
                "setting",
                "search"
              ]
            }
          },
          "response": []
        },
        {
          "name": "List",
          "request": {
            "method": "GET",
            "header": [],
            "url": {
              "raw": "http://localhost:8888/api/setting/list",
              "protocol": "http",
              "host": [
                "localhost"
              ],
              "port": "8888",
              "path": [
                "api",
                "setting",
                "list"
              ]
            }
          },
          "response": []
        },
        {
          "name": "List All",
          "request": {
            "method": "GET",
            "header": [],
            "url": {
              "raw": "http://localhost:8888/api/setting/listAll",
              "protocol": "http",
              "host": [
                "localhost"
              ],
              "port": "8888",
              "path": [
                "api",
                "setting",
                "listAll"
              ]
            }
          },
          "response": []
        },
        {
          "name": "Filter",
          "request": {
            "method": "GET",
            "header": [],
            "url": {
              "raw": "http://localhost:8888/api/setting/filter",
              "protocol": "http",
              "host": [
                "localhost"
              ],
              "port": "8888",
              "path": [
                "api",
                "setting",
                "filter"
              ]
            }
          },
          "response": []
        },
        {
          "name": "Read by Setting Key",
          "request": {
            "method": "GET",
            "header": [],
            "url": {
              "raw": "http://localhost:8888/api/setting/readBySettingKey/:settingKey",
              "protocol": "http",
              "host": [
                "localhost"
              ],
              "port": "8888",
              "path": [
                "api",
                "setting",
                "readBySettingKey",
                ":settingKey"
              ]
            }
          },
          "response": []
        },
        {
          "name": "List by Setting Key",
          "request": {
            "method": "GET",
            "header": [],
            "url": {
              "raw": "http://localhost:8888/api/setting/listBySettingKey",
              "protocol": "http",
              "host": [
                "localhost"
              ],
              "port": "8888",
              "path": [
                "api",
                "setting",
                "listBySettingKey"
              ]
            }
          },
          "response": []
        },
        {
          "name": "Update by Setting Key",
          "request": {
            "method": "PATCH",
            "header": [],
            "url": {
              "raw": "http://localhost:8888/api/setting/updateBySettingKey/:settingKey?",
              "protocol": "http",
              "host": [
                "localhost"
              ],
              "port": "8888",
              "path": [
                "api",
                "setting",
                "updateBySettingKey",
                ":settingKey?"
              ]
            }
          },
          "response": []
        },
        {
          "name": "Upload",
          "request": {
            "method": "PATCH",
            "header": [],
            "url": {
              "raw": "http://localhost:8888/api/setting/upload/:settingKey?",
              "protocol": "http",
              "host": [
                "localhost"
              ],
              "port": "8888",
              "path": [
                "api",
                "setting",
                "upload",
                ":settingKey?"
              ]
            }
          },
          "response": []
        },
        {
          "name": "Update Many Settings",
          "request": {
            "method": "PATCH",
            "header": [],
            "url": {
              "raw": "http://localhost:8888/api/setting/updateManySetting",
              "protocol": "http",
              "host": [
                "localhost"
              ],
              "port": "8888",
              "path": [
                "api",
                "setting",
                "updateManySetting"
              ]
            }
          },
          "response": []
        }
      ]
    },
    {
      "name": "Download",
      "item": [
        {
          "name": "File",
          "request": {
            "method": "GET",
            "header": [],
            "url": {
              "raw": "http://localhost:8888/download/:directory/:file",
              "protocol": "http",
              "host": [
                "localhost"
              ],
              "port": "8888",
              "path": [
                "download",
                ":directory",
                ":file"
              ]
            }
          },
          "response": []
        }
      ]
    },
    {
      "name": "Public",
      "item": [
        {
          "name": "File",
          "request": {
            "method": "GET",
            "header": [],
            "url": {
              "raw": "http://localhost:8888/public/:subPath/:directory/:file",
              "protocol": "http",
              "host": [
                "localhost"
              ],
              "port": "8888",
              "path": [
                "public",
                ":subPath",
                ":directory",
                ":file"
              ]
            }
          },
          "response": []
        }
      ]
    }
  ]
}
